geeViz/__init__.py
geeViz/assetManagerLib.py
geeViz/changeDetectionLib.py
geeViz/cloudStorageManagerLib.py
geeViz/foliumView.py
geeViz/gcpLib.py
geeViz/gee2Pandas.py
geeViz/geePalettes.py
geeViz/geeView.py
geeViz/getImagesLib.py
geeViz/migrateGEEAssets.py
geeViz/phEEnoViz.py
geeViz/taskManagerLib.py
geeViz/examples/Aboveground_Biomass_Viewer_Notebook.ipynb
geeViz/examples/Annual_NLCD_Viewer_Notebook.ipynb
geeViz/examples/CCDCViz.py
geeViz/examples/CCDCVizNotebook.ipynb
geeViz/examples/CCDCWrapper.py
geeViz/examples/GFSTimeLapse.py
geeViz/examples/LANDTRENDRViz.py
geeViz/examples/LANDTRENDRVizNotebook.ipynb
geeViz/examples/LANDTRENDRWrapper.py
geeViz/examples/LANDTRENDRWrapperNotebook.ipynb
geeViz/examples/LCMAP_and_LCMS_Viewer.py
geeViz/examples/LCMAP_and_LCMS_Viewer_Notebook.ipynb
geeViz/examples/LCMS_Levels_Viewer_Notebook.ipynb
geeViz/examples/__init__.py
geeViz/examples/areaChart_examples.ipynb
geeViz/examples/dynamicWorldExampleNotebook.ipynb
geeViz/examples/foliumViewerExample.py
geeViz/examples/gee2PandasExample.ipynb
geeViz/examples/geeViewExample.py
geeViz/examples/geeViewExampleNotebook.ipynb
geeViz/examples/geeViewVSFoliumViewerExampleNotebook.ipynb
geeViz/examples/geeViz_geeMap_comparison.py
geeViz/examples/geeViz_geeMap_comparison_tutorial.ipynb
geeViz/examples/getClimateWrapper.py
geeViz/examples/getCombinedLandsatSentinel2Wrapper.py
geeViz/examples/getLandsatWrapper.py
geeViz/examples/getLandsatWrapperNotebook.ipynb
geeViz/examples/getSentinel2Wrapper.py
geeViz/examples/global_land_cover_example_notebook.ipynb
geeViz/examples/harmonicRegressionWrapper.py
geeViz/examples/lcmsLevelLookup.py
geeViz/examples/lcmsViewerExample.py
geeViz/examples/lcmsViewerExampleNotebook.ipynb
geeViz/examples/mapBiomasLookup.py
geeViz/examples/mapBiomasViewerExample.py
geeViz/examples/mapBiomasViewerExampleNotebook.ipynb
geeViz/examples/phEEnoVizWrapper.py
geeViz/examples/taskTrackerExample.py
geeViz/examples/timeLapseExample.py
geeviz-2025.10.2.dist-info/licenses/LICENSE
geeviz-2025.10.2.dist-info/METADATA
geeviz-2025.10.2.dist-info/WHEEL
geeviz-2025.10.2.dist-info/top_level.txt
geeviz-2025.10.2.dist-info/RECORD
