Metadata-Version: 2.4
Name: geeviz
Version: 2025.10.2
Summary: A package to help with GEE data processing, analysis, and visualization
Author: Ian Housman
Author-email: ian.housman@gmail.com
License: Apache
Project-URL: Repository, https://github.com/gee-community/geeviz
Project-URL: Documentation, https://geeviz.org/
Keywords: google earth engine earthengine gee remote sensing landsat sentinel sentinel-2 modis forestry forest land cover use change detection nlcd
Classifier: Programming Language :: Python :: 3
Classifier: Intended Audience :: Science/Research
Classifier: License :: OSI Approved :: Apache Software License
Classifier: Operating System :: OS Independent
Classifier: Development Status :: 4 - Beta
License-File: LICENSE
Requires-Dist: earthengine-api
Requires-Dist: oauth2client
Requires-Dist: google-cloud-storage
Requires-Dist: pandas
Requires-Dist: geemap
Requires-Dist: matplotlib
Requires-Dist: IPython
Requires-Dist: requests
Requires-Dist: folium
Requires-Dist: simpledbf
Dynamic: author
Dynamic: author-email
Dynamic: classifier
Dynamic: description
Dynamic: description-content-type
Dynamic: keywords
Dynamic: license
Dynamic: license-file
Dynamic: project-url
Dynamic: requires-dist
Dynamic: summary
